pylfi/__init__.py
pylfi/__version__.py
pylfi/infer.py
pylfi/inferences_deprecated.py
pylfi/journal_deprecated.py
pylfi/densest/__init__.py
pylfi/densest/_bw_rules.py
pylfi/densest/base_kde.py
pylfi/densest/histogram.py
pylfi/densest/kde.py
pylfi/distances/__init__.py
pylfi/distances/distances.py
pylfi/features/__init__.py
pylfi/features/network_features.py
pylfi/features/spiking_features.py
pylfi/features/summary_statistics.py
pylfi/inferences/__init__.py
pylfi/inferences/abc_base.py
pylfi/inferences/mcmc_abc.py
pylfi/inferences/pmc_abc.py
pylfi/inferences/rejection_abc.py
pylfi/inferences/smc_abc.py
pylfi/journal/__init__.py
pylfi/journal/_checks.py
pylfi/journal/_journal_adjustment.py
pylfi/journal/_journal_base.py
pylfi/journal/_journal_plotting.py
pylfi/journal/_regressors.py
pylfi/journal/_utils.py
pylfi/journal/journal.py
pylfi/models/__init__.py
pylfi/models/brunel_network.py
pylfi/models/exponential_decay.py
pylfi/models/hodgkin_huxley.py
pylfi/models/lotka_volterra.py
pylfi/models/stimulus.py
pylfi/plots/__init__.py
pylfi/plots/plotting.py
pylfi/priors/__init__.py
pylfi/priors/prior_base.py
pylfi/priors/priors.py
pylfi/simulators/__init__.py
pylfi/simulators/hh_simulator.py
pylfi/utils/__init__.py
pylfi/utils/checks.py
pylfi/utils/logging_handler.py
pylfi/utils/stats.py
pylfi/utils/utils.py
pylfi-0.0.1.dist-info/LICENSE
pylfi-0.0.1.dist-info/METADATA
pylfi-0.0.1.dist-info/WHEEL
pylfi-0.0.1.dist-info/top_level.txt
pylfi-0.0.1.dist-info/RECORD
